beetsplug/covergrid/__about__.py
beetsplug/covergrid/__init__.py
beetsplug/covergrid/static/backbone.js
beetsplug/covergrid/static/beets.css
beetsplug/covergrid/static/beets.js
beetsplug/covergrid/static/jquery.js
beetsplug/covergrid/static/underscore.js
beetsplug/covergrid/templates/index.html
beetsplug_covergrid-0.0.7.dist-info/METADATA
beetsplug_covergrid-0.0.7.dist-info/WHEEL
beetsplug_covergrid-0.0.7.dist-info/licenses/LICENSE.txt
beetsplug_covergrid-0.0.7.dist-info/RECORD
