Metadata-Version: 2.4
Name: beetsplug-covergrid
Version: 0.0.7
Summary: A Beets plugin to show cover art in a grid in a web UI.
Project-URL: Homepage, https://source.tube/valrus/beetsplug-covergrid
Author-email: valrus <ian@mccowan.space>, Adrian Sampson <adrian@radbox.org>
Maintainer-email: valrus <ian@mccowan.space>
License-Expression: MIT
License-File: LICENSE.txt
Classifier: Development Status :: 3 - Alpha
Classifier: Programming Language :: Python
Classifier: Programming Language :: Python :: 3.8
Classifier: Programming Language :: Python :: 3.9
Classifier: Programming Language :: Python :: 3.10
Classifier: Programming Language :: Python :: 3.11
Classifier: Programming Language :: Python :: 3.12
Classifier: Programming Language :: Python :: 3.13
Classifier: Programming Language :: Python :: Implementation :: CPython
Classifier: Topic :: Multimedia :: Graphics :: Viewers
Classifier: Topic :: Multimedia :: Sound/Audio
Requires-Python: >=3.8
Requires-Dist: beets>=2.4.0
Requires-Dist: flask
Provides-Extra: dev
Requires-Dist: mypy; extra == 'dev'
Requires-Dist: pylsp-mypy; extra == 'dev'
Requires-Dist: python-lsp-server; extra == 'dev'
Requires-Dist: ruff; extra == 'dev'
Provides-Extra: test
Requires-Dist: pytest; extra == 'test'
